{"resourceType":"Bundle","type":"transaction","entry":[{"fullUrl":"urn:uuid:6e05b758-43e0-4c79-b0bb-0c4a5923976d","resource":{"resourceType":"Patient","id":"6e05b758-43e0-4c79-b0bb-0c4a5923976d","meta":{"profile":["http://hl7.org/fhir/us/core/StructureDefinition/us-core-patient"]},"identifier":[{"system":"urn:trialmatchrx:patient","value":"PAT0350"}],"name":[{"use":"official","family":"PAT0350"}],"gender":"male","birthDate":"1973-01-01"},"request":{"method":"POST","url":"Patient"}},{"fullUrl":"urn:uuid:78dd14c0-528c-4d93-ab44-f6b82364c1d8","resource":{"resourceType":"Encounter","id":"78dd14c0-528c-4d93-ab44-f6b82364c1d8","status":"finished","class":{"system":"http://terminology.hl7.org/CodeSystem/v3-ActCode","code":"AMB"},"period":{"start":"2025-09-18","end":"2025-09-18"},"subject":{"reference":"urn:uuid:6e05b758-43e0-4c79-b0bb-0c4a5923976d"}},"request":{"method":"POST","url":"Encounter"}},{"fullUrl":"urn:uuid:ef264386-af0d-45e7-b7ed-a86264f77b62","resource":{"resourceType":"Condition","id":"ef264386-af0d-45e7-b7ed-a86264f77b62","clinicalStatus":{"coding":[{"system":"http://terminology.hl7.org/CodeSystem/condition-clinical","code":"active"}]},"verificationStatus":{"coding":[{"system":"http://terminology.hl7.org/CodeSystem/condition-ver-status","code":"confirmed"}]},"category":[{"coding":[{"system":"http://terminology.hl7.org/CodeSystem/condition-category","code":"problem-list-item"}]}],"code":{"coding":[{"system":"http://hl7.org/fhir/sid/icd-10-cm","code":"C34.10","display":"Malignant neoplasm of upper lobe, bronchus or lung, unspecified side"},{"system":"http://snomed.info/sct","code":"254637007","display":"Non-small cell carcinoma of lung"}],"text":"Lung Cancer"},"subject":{"reference":"urn:uuid:6e05b758-43e0-4c79-b0bb-0c4a5923976d"},"onsetDateTime":"2025-09-18"},"request":{"method":"POST","url":"Condition"}},{"fullUrl":"urn:uuid:fc12cb03-14a7-488b-ad0b-c42fce9ea6a2","resource":{"resourceType":"Observation","id":"fc12cb03-14a7-488b-ad0b-c42fce9ea6a2","status":"final","category":[{"coding":[{"system":"http://terminology.hl7.org/CodeSystem/observation-category","code":"laboratory"}]}],"code":{"coding":[{"system":"http://loinc.org","code":"1920-8","display":"Aspartate aminotransferase [Enzymatic activity/volume] in Serum or Plasma"}],"text":"Aspartate aminotransferase [Enzymatic activity/volume] in Serum or Plasma"},"subject":{"reference":"urn:uuid:6e05b758-43e0-4c79-b0bb-0c4a5923976d"},"effectiveDateTime":"2025-09-18","valueQuantity":{"value":95.4,"unit":"U/L","system":"http://unitsofmeasure.org"}},"request":{"method":"POST","url":"Observation"}},{"fullUrl":"urn:uuid:7de86b3e-3bf7-4a44-aba1-f92be07079f1","resource":{"resourceType":"Observation","id":"7de86b3e-3bf7-4a44-aba1-f92be07079f1","status":"final","category":[{"coding":[{"system":"http://terminology.hl7.org/CodeSystem/observation-category","code":"laboratory"}]}],"code":{"coding":[{"system":"http://loinc.org","code":"1742-6","display":"Alanine aminotransferase [Enzymatic activity/volume] in Serum or Plasma"}],"text":"Alanine aminotransferase [Enzymatic activity/volume] in Serum or Plasma"},"subject":{"reference":"urn:uuid:6e05b758-43e0-4c79-b0bb-0c4a5923976d"},"effectiveDateTime":"2025-09-18","valueQuantity":{"value":57.16,"unit":"U/L","system":"http://unitsofmeasure.org"}},"request":{"method":"POST","url":"Observation"}},{"fullUrl":"urn:uuid:7443cc1a-74e5-4e6e-a6cc-921fc005248b","resource":{"resourceType":"Observation","id":"7443cc1a-74e5-4e6e-a6cc-921fc005248b","status":"final","category":[{"coding":[{"system":"http://terminology.hl7.org/CodeSystem/observation-category","code":"laboratory"}]}],"code":{"coding":[{"system":"http://loinc.org","code":"2160-0","display":"Creatinine [Mass/volume] in Serum or Plasma"}],"text":"Creatinine [Mass/volume] in Serum or Plasma"},"subject":{"reference":"urn:uuid:6e05b758-43e0-4c79-b0bb-0c4a5923976d"},"effectiveDateTime":"2025-09-18","valueQuantity":{"value":1.73,"unit":"mg/dL","system":"http://unitsofmeasure.org"}},"request":{"method":"POST","url":"Observation"}},{"fullUrl":"urn:uuid:d0cc6ff3-c33b-4644-be71-6c16fceafab0","resource":{"resourceType":"Observation","id":"d0cc6ff3-c33b-4644-be71-6c16fceafab0","status":"final","category":[{"coding":[{"system":"http://terminology.hl7.org/CodeSystem/observation-category","code":"laboratory"}]}],"code":{"coding":[{"system":"http://loinc.org","code":"718-7","display":"Hemoglobin [Mass/volume] in Blood"}],"text":"Hemoglobin [Mass/volume] in Blood"},"subject":{"reference":"urn:uuid:6e05b758-43e0-4c79-b0bb-0c4a5923976d"},"effectiveDateTime":"2025-09-18","valueQuantity":{"value":12.12,"unit":"g/dL","system":"http://unitsofmeasure.org"}},"request":{"method":"POST","url":"Observation"}},{"fullUrl":"urn:uuid:7855b2ad-0cc1-416a-8709-7c0cb6e6b268","resource":{"resourceType":"Observation","id":"7855b2ad-0cc1-416a-8709-7c0cb6e6b268","status":"final","category":[{"coding":[{"system":"http://terminology.hl7.org/CodeSystem/observation-category","code":"laboratory"}]}],"code":{"coding":[{"system":"http://loinc.org","code":"777-3","display":"Platelets [#/volume] in Blood by Automated count"}],"text":"Platelets [#/volume] in Blood by Automated count"},"subject":{"reference":"urn:uuid:6e05b758-43e0-4c79-b0bb-0c4a5923976d"},"effectiveDateTime":"2025-09-18","valueQuantity":{"value":426.55,"unit":"10*9/L","system":"http://unitsofmeasure.org"}},"request":{"method":"POST","url":"Observation"}},{"fullUrl":"urn:uuid:1fd4d618-035f-4cdb-b126-f4e17647c337","resource":{"resourceType":"Observation","id":"1fd4d618-035f-4cdb-b126-f4e17647c337","status":"final","category":[{"coding":[{"system":"http://terminology.hl7.org/CodeSystem/observation-category","code":"laboratory"}]}],"code":{"coding":[{"system":"http://loinc.org","code":"6690-2","display":"Leukocytes [#/volume] in Blood by Automated count"}],"text":"Leukocytes [#/volume] in Blood by Automated count"},"subject":{"reference":"urn:uuid:6e05b758-43e0-4c79-b0bb-0c4a5923976d"},"effectiveDateTime":"2025-09-18","valueQuantity":{"value":14.15,"unit":"10*9/L","system":"http://unitsofmeasure.org"}},"request":{"method":"POST","url":"Observation"}},{"fullUrl":"urn:uuid:6b2116e7-3e1a-413c-9563-6e2ea8a9f24d","resource":{"resourceType":"Observation","id":"6b2116e7-3e1a-413c-9563-6e2ea8a9f24d","status":"final","category":[{"coding":[{"system":"http://terminology.hl7.org/CodeSystem/observation-category","code":"laboratory"}]}],"code":{"coding":[{"system":"http://loinc.org","code":"55201-8","display":"EGFR gene mutation analysis"}],"text":"EGFR gene mutation analysis"},"subject":{"reference":"urn:uuid:6e05b758-43e0-4c79-b0bb-0c4a5923976d"},"effectiveDateTime":"2025-09-18","valueCodeableConcept":{"coding":[{"system":"http://snomed.info/sct","code":"10828004","display":"Positive"}],"text":"Positive"}},"request":{"method":"POST","url":"Observation"}},{"fullUrl":"urn:uuid:f3e0fa47-a4df-4ae0-ac53-aa8ffe4e9862","resource":{"resourceType":"Procedure","id":"f3e0fa47-a4df-4ae0-ac53-aa8ffe4e9862","status":"completed","code":{"coding":[{"system":"http://snomed.info/sct","code":"367336001","display":"Chemotherapy"}],"text":"Chemotherapy"},"subject":{"reference":"urn:uuid:6e05b758-43e0-4c79-b0bb-0c4a5923976d"},"performedDateTime":"2025-09-18"},"request":{"method":"POST","url":"Procedure"}},{"fullUrl":"urn:uuid:50df9981-0d0d-4184-a25d-964697e0e74c","resource":{"resourceType":"Procedure","id":"50df9981-0d0d-4184-a25d-964697e0e74c","status":"completed","code":{"coding":[{"system":"http://snomed.info/sct","code":"33195004","display":"Radiation therapy"}],"text":"Radiation therapy"},"subject":{"reference":"urn:uuid:6e05b758-43e0-4c79-b0bb-0c4a5923976d"},"performedDateTime":"2025-09-18"},"request":{"method":"POST","url":"Procedure"}},{"fullUrl":"urn:uuid:9ce46d87-7de0-47e9-9706-cec15b58aca1","resource":{"resourceType":"Procedure","id":"9ce46d87-7de0-47e9-9706-cec15b58aca1","status":"completed","code":{"coding":[{"system":"http://snomed.info/sct","code":"169413002","display":"Hormone therapy"}],"text":"Hormone therapy"},"subject":{"reference":"urn:uuid:6e05b758-43e0-4c79-b0bb-0c4a5923976d"},"performedDateTime":"2025-09-18"},"request":{"method":"POST","url":"Procedure"}}]}