{"resourceType":"Bundle","type":"transaction","entry":[{"fullUrl":"urn:uuid:26e18f15-b31f-46ae-962a-f89975ccfb24","resource":{"resourceType":"Patient","id":"26e18f15-b31f-46ae-962a-f89975ccfb24","meta":{"profile":["http://hl7.org/fhir/us/core/StructureDefinition/us-core-patient"]},"identifier":[{"system":"urn:trialmatchrx:patient","value":"PAT0250"}],"name":[{"use":"official","family":"PAT0250"}],"gender":"female","birthDate":"1939-01-01"},"request":{"method":"POST","url":"Patient"}},{"fullUrl":"urn:uuid:9c49dae9-4283-47cb-892a-502929018cf5","resource":{"resourceType":"Encounter","id":"9c49dae9-4283-47cb-892a-502929018cf5","status":"finished","class":{"system":"http://terminology.hl7.org/CodeSystem/v3-ActCode","code":"AMB"},"period":{"start":"2025-07-30","end":"2025-07-30"},"subject":{"reference":"urn:uuid:26e18f15-b31f-46ae-962a-f89975ccfb24"}},"request":{"method":"POST","url":"Encounter"}},{"fullUrl":"urn:uuid:f8cf82a3-e884-44f8-9635-17b8843ccbfe","resource":{"resourceType":"Condition","id":"f8cf82a3-e884-44f8-9635-17b8843ccbfe","clinicalStatus":{"coding":[{"system":"http://terminology.hl7.org/CodeSystem/condition-clinical","code":"active"}]},"verificationStatus":{"coding":[{"system":"http://terminology.hl7.org/CodeSystem/condition-ver-status","code":"confirmed"}]},"category":[{"coding":[{"system":"http://terminology.hl7.org/CodeSystem/condition-category","code":"problem-list-item"}]}],"code":{"coding":[{"system":"http://hl7.org/fhir/sid/icd-10-cm","code":"C61","display":"Malignant neoplasm of prostate"},{"system":"http://snomed.info/sct","code":"399068003","display":"Malignant tumor of prostate"}],"text":"Prostate Cancer"},"subject":{"reference":"urn:uuid:26e18f15-b31f-46ae-962a-f89975ccfb24"},"onsetDateTime":"2025-07-30"},"request":{"method":"POST","url":"Condition"}},{"fullUrl":"urn:uuid:d610109f-882e-45ad-b489-298e76ddc307","resource":{"resourceType":"Observation","id":"d610109f-882e-45ad-b489-298e76ddc307","status":"final","category":[{"coding":[{"system":"http://terminology.hl7.org/CodeSystem/observation-category","code":"laboratory"}]}],"code":{"coding":[{"system":"http://loinc.org","code":"1920-8","display":"Aspartate aminotransferase [Enzymatic activity/volume] in Serum or Plasma"}],"text":"Aspartate aminotransferase [Enzymatic activity/volume] in Serum or Plasma"},"subject":{"reference":"urn:uuid:26e18f15-b31f-46ae-962a-f89975ccfb24"},"effectiveDateTime":"2025-07-30","valueQuantity":{"value":94.63,"unit":"U/L","system":"http://unitsofmeasure.org"}},"request":{"method":"POST","url":"Observation"}},{"fullUrl":"urn:uuid:6ff1d171-2fc8-4932-ba6f-4904185f69dd","resource":{"resourceType":"Observation","id":"6ff1d171-2fc8-4932-ba6f-4904185f69dd","status":"final","category":[{"coding":[{"system":"http://terminology.hl7.org/CodeSystem/observation-category","code":"laboratory"}]}],"code":{"coding":[{"system":"http://loinc.org","code":"1742-6","display":"Alanine aminotransferase [Enzymatic activity/volume] in Serum or Plasma"}],"text":"Alanine aminotransferase [Enzymatic activity/volume] in Serum or Plasma"},"subject":{"reference":"urn:uuid:26e18f15-b31f-46ae-962a-f89975ccfb24"},"effectiveDateTime":"2025-07-30","valueQuantity":{"value":25.67,"unit":"U/L","system":"http://unitsofmeasure.org"}},"request":{"method":"POST","url":"Observation"}},{"fullUrl":"urn:uuid:c82c8093-5a9a-4be1-901d-da6b1e6aa458","resource":{"resourceType":"Observation","id":"c82c8093-5a9a-4be1-901d-da6b1e6aa458","status":"final","category":[{"coding":[{"system":"http://terminology.hl7.org/CodeSystem/observation-category","code":"laboratory"}]}],"code":{"coding":[{"system":"http://loinc.org","code":"2160-0","display":"Creatinine [Mass/volume] in Serum or Plasma"}],"text":"Creatinine [Mass/volume] in Serum or Plasma"},"subject":{"reference":"urn:uuid:26e18f15-b31f-46ae-962a-f89975ccfb24"},"effectiveDateTime":"2025-07-30","valueQuantity":{"value":1.88,"unit":"mg/dL","system":"http://unitsofmeasure.org"}},"request":{"method":"POST","url":"Observation"}},{"fullUrl":"urn:uuid:431cffcd-b91f-4f93-b4ae-fece3ebaaf3e","resource":{"resourceType":"Observation","id":"431cffcd-b91f-4f93-b4ae-fece3ebaaf3e","status":"final","category":[{"coding":[{"system":"http://terminology.hl7.org/CodeSystem/observation-category","code":"laboratory"}]}],"code":{"coding":[{"system":"http://loinc.org","code":"718-7","display":"Hemoglobin [Mass/volume] in Blood"}],"text":"Hemoglobin [Mass/volume] in Blood"},"subject":{"reference":"urn:uuid:26e18f15-b31f-46ae-962a-f89975ccfb24"},"effectiveDateTime":"2025-07-30","valueQuantity":{"value":17.12,"unit":"g/dL","system":"http://unitsofmeasure.org"}},"request":{"method":"POST","url":"Observation"}},{"fullUrl":"urn:uuid:d8ff5902-284a-4b8f-9a16-c7a5d6d67630","resource":{"resourceType":"Observation","id":"d8ff5902-284a-4b8f-9a16-c7a5d6d67630","status":"final","category":[{"coding":[{"system":"http://terminology.hl7.org/CodeSystem/observation-category","code":"laboratory"}]}],"code":{"coding":[{"system":"http://loinc.org","code":"777-3","display":"Platelets [#/volume] in Blood by Automated count"}],"text":"Platelets [#/volume] in Blood by Automated count"},"subject":{"reference":"urn:uuid:26e18f15-b31f-46ae-962a-f89975ccfb24"},"effectiveDateTime":"2025-07-30","valueQuantity":{"value":321.67,"unit":"10*9/L","system":"http://unitsofmeasure.org"}},"request":{"method":"POST","url":"Observation"}},{"fullUrl":"urn:uuid:dacfa0ef-14e3-4d41-a6ac-c401ec40d5b7","resource":{"resourceType":"Observation","id":"dacfa0ef-14e3-4d41-a6ac-c401ec40d5b7","status":"final","category":[{"coding":[{"system":"http://terminology.hl7.org/CodeSystem/observation-category","code":"laboratory"}]}],"code":{"coding":[{"system":"http://loinc.org","code":"6690-2","display":"Leukocytes [#/volume] in Blood by Automated count"}],"text":"Leukocytes [#/volume] in Blood by Automated count"},"subject":{"reference":"urn:uuid:26e18f15-b31f-46ae-962a-f89975ccfb24"},"effectiveDateTime":"2025-07-30","valueQuantity":{"value":2.6,"unit":"10*9/L","system":"http://unitsofmeasure.org"}},"request":{"method":"POST","url":"Observation"}},{"fullUrl":"urn:uuid:21e2ec17-2c4e-433d-9da7-234dfbe05f99","resource":{"resourceType":"Procedure","id":"21e2ec17-2c4e-433d-9da7-234dfbe05f99","status":"completed","code":{"coding":[{"system":"http://snomed.info/sct","code":"367336001","display":"Chemotherapy"}],"text":"Chemotherapy"},"subject":{"reference":"urn:uuid:26e18f15-b31f-46ae-962a-f89975ccfb24"},"performedDateTime":"2025-07-30"},"request":{"method":"POST","url":"Procedure"}},{"fullUrl":"urn:uuid:5c26c808-95dc-43e6-b9b4-c7c9b5dc7094","resource":{"resourceType":"Procedure","id":"5c26c808-95dc-43e6-b9b4-c7c9b5dc7094","status":"completed","code":{"coding":[{"system":"http://snomed.info/sct","code":"416608005","display":"Targeted therapy"}],"text":"Targeted therapy"},"subject":{"reference":"urn:uuid:26e18f15-b31f-46ae-962a-f89975ccfb24"},"performedDateTime":"2025-07-30"},"request":{"method":"POST","url":"Procedure"}},{"fullUrl":"urn:uuid:8d65ccd2-61ca-4ec9-9fe8-a4e9d7bddf6e","resource":{"resourceType":"Procedure","id":"8d65ccd2-61ca-4ec9-9fe8-a4e9d7bddf6e","status":"completed","code":{"coding":[{"system":"http://snomed.info/sct","code":"33195004","display":"Radiation therapy"}],"text":"Radiation therapy"},"subject":{"reference":"urn:uuid:26e18f15-b31f-46ae-962a-f89975ccfb24"},"performedDateTime":"2025-07-30"},"request":{"method":"POST","url":"Procedure"}}]}