{"resourceType":"Bundle","type":"transaction","entry":[{"fullUrl":"urn:uuid:38744b60-b127-431b-81d1-fe4828448404","resource":{"resourceType":"Patient","id":"38744b60-b127-431b-81d1-fe4828448404","identifier":[{"system":"urn:trialmatchrx:patient","value":"PAT0972"}],"name":[{"use":"official","family":"PAT0972"}],"gender":"male","birthDate":"1985-01-01"},"request":{"method":"POST","url":"Patient"}},{"fullUrl":"urn:uuid:662f0370-1a7a-42c8-975d-dc1a9be3d265","resource":{"resourceType":"Encounter","id":"662f0370-1a7a-42c8-975d-dc1a9be3d265","status":"finished","class":{"system":"http://terminology.hl7.org/CodeSystem/v3-ActCode","code":"AMB"},"period":{"start":"2025-03-21","end":"2025-03-21"},"subject":{"reference":"urn:uuid:38744b60-b127-431b-81d1-fe4828448404"}},"request":{"method":"POST","url":"Encounter"}},{"fullUrl":"urn:uuid:20c9c5e9-f5a2-418a-bbd2-c6ae4effaf72","resource":{"resourceType":"Condition","id":"20c9c5e9-f5a2-418a-bbd2-c6ae4effaf72","clinicalStatus":{"coding":[{"system":"http://terminology.hl7.org/CodeSystem/condition-clinical","code":"active"}]},"verificationStatus":{"coding":[{"system":"http://terminology.hl7.org/CodeSystem/condition-ver-status","code":"confirmed"}]},"category":[{"coding":[{"system":"http://terminology.hl7.org/CodeSystem/condition-category","code":"problem-list-item"}]}],"code":{"coding":[{"system":"http://hl7.org/fhir/sid/icd-10-cm","code":"C34.10","display":"Malignant neoplasm of lung"},{"system":"http://snomed.info/sct","code":"254637007","display":"Non-small cell carcinoma of lung"}],"text":"Lung Cancer"},"subject":{"reference":"urn:uuid:38744b60-b127-431b-81d1-fe4828448404"},"onsetDateTime":"2025-03-21"},"request":{"method":"POST","url":"Condition"}},{"fullUrl":"urn:uuid:f2c76936-7840-4c70-baf1-f3e93c4606ea","resource":{"resourceType":"Observation","id":"f2c76936-7840-4c70-baf1-f3e93c4606ea","status":"final","category":[{"coding":[{"system":"http://terminology.hl7.org/CodeSystem/observation-category","code":"laboratory"}]}],"code":{"coding":[{"system":"http://loinc.org","code":"1920-8","display":"Aspartate aminotransferase"}],"text":"Aspartate aminotransferase"},"subject":{"reference":"urn:uuid:38744b60-b127-431b-81d1-fe4828448404"},"effectiveDateTime":"2025-03-21","valueQuantity":{"value":68.45,"unit":"U/L","system":"http://unitsofmeasure.org"}},"request":{"method":"POST","url":"Observation"}},{"fullUrl":"urn:uuid:db1cb81e-cbab-4ff8-bc24-fc798be2199a","resource":{"resourceType":"Observation","id":"db1cb81e-cbab-4ff8-bc24-fc798be2199a","status":"final","category":[{"coding":[{"system":"http://terminology.hl7.org/CodeSystem/observation-category","code":"laboratory"}]}],"code":{"coding":[{"system":"http://loinc.org","code":"1742-6","display":"Alanine aminotransferase"}],"text":"Alanine aminotransferase"},"subject":{"reference":"urn:uuid:38744b60-b127-431b-81d1-fe4828448404"},"effectiveDateTime":"2025-03-21","valueQuantity":{"value":19.67,"unit":"U/L","system":"http://unitsofmeasure.org"}},"request":{"method":"POST","url":"Observation"}},{"fullUrl":"urn:uuid:a4e71420-d80f-4e92-8f98-3afedcc94de6","resource":{"resourceType":"Observation","id":"a4e71420-d80f-4e92-8f98-3afedcc94de6","status":"final","category":[{"coding":[{"system":"http://terminology.hl7.org/CodeSystem/observation-category","code":"laboratory"}]}],"code":{"coding":[{"system":"http://loinc.org","code":"2160-0","display":"Creatinine"}],"text":"Creatinine"},"subject":{"reference":"urn:uuid:38744b60-b127-431b-81d1-fe4828448404"},"effectiveDateTime":"2025-03-21","valueQuantity":{"value":1.41,"unit":"mg/dL","system":"http://unitsofmeasure.org"}},"request":{"method":"POST","url":"Observation"}},{"fullUrl":"urn:uuid:17a4825a-3e52-4894-882a-2a0db543270d","resource":{"resourceType":"Observation","id":"17a4825a-3e52-4894-882a-2a0db543270d","status":"final","category":[{"coding":[{"system":"http://terminology.hl7.org/CodeSystem/observation-category","code":"laboratory"}]}],"code":{"coding":[{"system":"http://loinc.org","code":"718-7","display":"Hemoglobin"}],"text":"Hemoglobin"},"subject":{"reference":"urn:uuid:38744b60-b127-431b-81d1-fe4828448404"},"effectiveDateTime":"2025-03-21","valueQuantity":{"value":11.74,"unit":"g/dL","system":"http://unitsofmeasure.org"}},"request":{"method":"POST","url":"Observation"}},{"fullUrl":"urn:uuid:2f9c3c96-8c14-4975-897e-7207393e6c26","resource":{"resourceType":"Observation","id":"2f9c3c96-8c14-4975-897e-7207393e6c26","status":"final","category":[{"coding":[{"system":"http://terminology.hl7.org/CodeSystem/observation-category","code":"laboratory"}]}],"code":{"coding":[{"system":"http://loinc.org","code":"777-3","display":"Platelets"}],"text":"Platelets"},"subject":{"reference":"urn:uuid:38744b60-b127-431b-81d1-fe4828448404"},"effectiveDateTime":"2025-03-21","valueQuantity":{"value":203.97,"unit":"10*9/L","system":"http://unitsofmeasure.org"}},"request":{"method":"POST","url":"Observation"}},{"fullUrl":"urn:uuid:abeb2b76-811e-40b2-b562-03a050995bf5","resource":{"resourceType":"Observation","id":"abeb2b76-811e-40b2-b562-03a050995bf5","status":"final","category":[{"coding":[{"system":"http://terminology.hl7.org/CodeSystem/observation-category","code":"laboratory"}]}],"code":{"coding":[{"system":"http://loinc.org","code":"6690-2","display":"Leukocytes"}],"text":"Leukocytes"},"subject":{"reference":"urn:uuid:38744b60-b127-431b-81d1-fe4828448404"},"effectiveDateTime":"2025-03-21","valueQuantity":{"value":14.14,"unit":"10*9/L","system":"http://unitsofmeasure.org"}},"request":{"method":"POST","url":"Observation"}},{"fullUrl":"urn:uuid:3f31858e-de4a-4f22-b05f-ea3fa2140859","resource":{"resourceType":"Observation","id":"3f31858e-de4a-4f22-b05f-ea3fa2140859","status":"final","category":[{"coding":[{"system":"http://terminology.hl7.org/CodeSystem/observation-category","code":"laboratory"}]}],"code":{"coding":[{"system":"http://loinc.org","code":"55201-8","display":"EGFR gene mutation analysis"}],"text":"EGFR gene mutation analysis"},"subject":{"reference":"urn:uuid:38744b60-b127-431b-81d1-fe4828448404"},"effectiveDateTime":"2025-03-21","valueCodeableConcept":{"coding":[{"system":"http://snomed.info/sct","code":"10828004","display":"Positive"}],"text":"Positive"}},"request":{"method":"POST","url":"Observation"}},{"fullUrl":"urn:uuid:c74ef48c-e8b1-4fac-9a8c-76adab3b70f3","resource":{"resourceType":"Procedure","id":"c74ef48c-e8b1-4fac-9a8c-76adab3b70f3","status":"completed","code":{"coding":[{"system":"http://snomed.info/sct","code":"76334006","display":"Immunotherapy"}],"text":"Immunotherapy"},"subject":{"reference":"urn:uuid:38744b60-b127-431b-81d1-fe4828448404"},"performedDateTime":"2025-03-21"},"request":{"method":"POST","url":"Procedure"}},{"fullUrl":"urn:uuid:75cc5b3a-3a8c-42cc-82d7-135955d5e5d1","resource":{"resourceType":"Procedure","id":"75cc5b3a-3a8c-42cc-82d7-135955d5e5d1","status":"completed","code":{"coding":[{"system":"http://snomed.info/sct","code":"33195004","display":"Radiation therapy"}],"text":"Radiation therapy"},"subject":{"reference":"urn:uuid:38744b60-b127-431b-81d1-fe4828448404"},"performedDateTime":"2025-03-21"},"request":{"method":"POST","url":"Procedure"}},{"fullUrl":"urn:uuid:7e6d7118-1288-435a-a407-4fe00cca559c","resource":{"resourceType":"Procedure","id":"7e6d7118-1288-435a-a407-4fe00cca559c","status":"completed","code":{"coding":[{"system":"http://snomed.info/sct","code":"169413002","display":"Hormone therapy"}],"text":"Hormone therapy"},"subject":{"reference":"urn:uuid:38744b60-b127-431b-81d1-fe4828448404"},"performedDateTime":"2025-03-21"},"request":{"method":"POST","url":"Procedure"}}]}