{"resourceType":"Bundle","type":"transaction","entry":[{"fullUrl":"urn:uuid:a81be02c-7c3b-4bd1-83cd-f917ce22fea3","resource":{"resourceType":"Patient","id":"a81be02c-7c3b-4bd1-83cd-f917ce22fea3","identifier":[{"system":"urn:trialmatchrx:patient","value":"PAT0027"}],"name":[{"use":"official","family":"PAT0027"}],"gender":"female","birthDate":"1967-01-01"},"request":{"method":"POST","url":"Patient"}},{"fullUrl":"urn:uuid:b6a6909f-3ad0-41fb-89be-c35542f631a3","resource":{"resourceType":"Encounter","id":"b6a6909f-3ad0-41fb-89be-c35542f631a3","status":"finished","class":{"system":"http://terminology.hl7.org/CodeSystem/v3-ActCode","code":"AMB"},"period":{"start":"2025-10-03","end":"2025-10-03"},"subject":{"reference":"urn:uuid:a81be02c-7c3b-4bd1-83cd-f917ce22fea3"}},"request":{"method":"POST","url":"Encounter"}},{"fullUrl":"urn:uuid:68a3690f-88bf-4758-bcb2-fffc8645c605","resource":{"resourceType":"Condition","id":"68a3690f-88bf-4758-bcb2-fffc8645c605","clinicalStatus":{"coding":[{"system":"http://terminology.hl7.org/CodeSystem/condition-clinical","code":"active"}]},"verificationStatus":{"coding":[{"system":"http://terminology.hl7.org/CodeSystem/condition-ver-status","code":"confirmed"}]},"category":[{"coding":[{"system":"http://terminology.hl7.org/CodeSystem/condition-category","code":"problem-list-item"}]}],"code":{"coding":[{"system":"http://hl7.org/fhir/sid/icd-10-cm","code":"C56.9","display":"Malignant neoplasm of ovary"},{"system":"http://snomed.info/sct","code":"363443007","display":"Malignant tumor of ovary"}],"text":"Ovarian Cancer"},"subject":{"reference":"urn:uuid:a81be02c-7c3b-4bd1-83cd-f917ce22fea3"},"onsetDateTime":"2025-10-03"},"request":{"method":"POST","url":"Condition"}},{"fullUrl":"urn:uuid:c5b4d96f-38d5-4ffd-bc3f-e7726b4dc9ad","resource":{"resourceType":"Observation","id":"c5b4d96f-38d5-4ffd-bc3f-e7726b4dc9ad","status":"final","category":[{"coding":[{"system":"http://terminology.hl7.org/CodeSystem/observation-category","code":"laboratory"}]}],"code":{"coding":[{"system":"http://loinc.org","code":"1920-8","display":"Aspartate aminotransferase"}],"text":"Aspartate aminotransferase"},"subject":{"reference":"urn:uuid:a81be02c-7c3b-4bd1-83cd-f917ce22fea3"},"effectiveDateTime":"2025-10-03","valueQuantity":{"value":28.88,"unit":"U/L","system":"http://unitsofmeasure.org"}},"request":{"method":"POST","url":"Observation"}},{"fullUrl":"urn:uuid:ba96ba3f-17f8-49c7-88d6-3a6a6cea8b4d","resource":{"resourceType":"Observation","id":"ba96ba3f-17f8-49c7-88d6-3a6a6cea8b4d","status":"final","category":[{"coding":[{"system":"http://terminology.hl7.org/CodeSystem/observation-category","code":"laboratory"}]}],"code":{"coding":[{"system":"http://loinc.org","code":"1742-6","display":"Alanine aminotransferase"}],"text":"Alanine aminotransferase"},"subject":{"reference":"urn:uuid:a81be02c-7c3b-4bd1-83cd-f917ce22fea3"},"effectiveDateTime":"2025-10-03","valueQuantity":{"value":66.7,"unit":"U/L","system":"http://unitsofmeasure.org"}},"request":{"method":"POST","url":"Observation"}},{"fullUrl":"urn:uuid:698d3c1d-9f1d-4fdb-a727-71e9f97bc3f2","resource":{"resourceType":"Observation","id":"698d3c1d-9f1d-4fdb-a727-71e9f97bc3f2","status":"final","category":[{"coding":[{"system":"http://terminology.hl7.org/CodeSystem/observation-category","code":"laboratory"}]}],"code":{"coding":[{"system":"http://loinc.org","code":"2160-0","display":"Creatinine"}],"text":"Creatinine"},"subject":{"reference":"urn:uuid:a81be02c-7c3b-4bd1-83cd-f917ce22fea3"},"effectiveDateTime":"2025-10-03","valueQuantity":{"value":1.55,"unit":"mg/dL","system":"http://unitsofmeasure.org"}},"request":{"method":"POST","url":"Observation"}},{"fullUrl":"urn:uuid:96a8673a-ef13-40d1-a9d8-99443e05539f","resource":{"resourceType":"Observation","id":"96a8673a-ef13-40d1-a9d8-99443e05539f","status":"final","category":[{"coding":[{"system":"http://terminology.hl7.org/CodeSystem/observation-category","code":"laboratory"}]}],"code":{"coding":[{"system":"http://loinc.org","code":"718-7","display":"Hemoglobin"}],"text":"Hemoglobin"},"subject":{"reference":"urn:uuid:a81be02c-7c3b-4bd1-83cd-f917ce22fea3"},"effectiveDateTime":"2025-10-03","valueQuantity":{"value":10.18,"unit":"g/dL","system":"http://unitsofmeasure.org"}},"request":{"method":"POST","url":"Observation"}},{"fullUrl":"urn:uuid:ca21358e-f977-4ad4-a4e0-30f2f35395d6","resource":{"resourceType":"Observation","id":"ca21358e-f977-4ad4-a4e0-30f2f35395d6","status":"final","category":[{"coding":[{"system":"http://terminology.hl7.org/CodeSystem/observation-category","code":"laboratory"}]}],"code":{"coding":[{"system":"http://loinc.org","code":"777-3","display":"Platelets"}],"text":"Platelets"},"subject":{"reference":"urn:uuid:a81be02c-7c3b-4bd1-83cd-f917ce22fea3"},"effectiveDateTime":"2025-10-03","valueQuantity":{"value":184.1,"unit":"10*9/L","system":"http://unitsofmeasure.org"}},"request":{"method":"POST","url":"Observation"}},{"fullUrl":"urn:uuid:d072dad6-e9d9-456e-a21d-ded7e46e4a20","resource":{"resourceType":"Observation","id":"d072dad6-e9d9-456e-a21d-ded7e46e4a20","status":"final","category":[{"coding":[{"system":"http://terminology.hl7.org/CodeSystem/observation-category","code":"laboratory"}]}],"code":{"coding":[{"system":"http://loinc.org","code":"6690-2","display":"Leukocytes"}],"text":"Leukocytes"},"subject":{"reference":"urn:uuid:a81be02c-7c3b-4bd1-83cd-f917ce22fea3"},"effectiveDateTime":"2025-10-03","valueQuantity":{"value":3.67,"unit":"10*9/L","system":"http://unitsofmeasure.org"}},"request":{"method":"POST","url":"Observation"}},{"fullUrl":"urn:uuid:60c400f4-d1c7-4b36-aca0-85d808ed1581","resource":{"resourceType":"Procedure","id":"60c400f4-d1c7-4b36-aca0-85d808ed1581","status":"completed","code":{"coding":[{"system":"http://snomed.info/sct","code":"387713003","display":"Surgical procedure"}],"text":"Surgical procedure"},"subject":{"reference":"urn:uuid:a81be02c-7c3b-4bd1-83cd-f917ce22fea3"},"performedDateTime":"2025-10-03"},"request":{"method":"POST","url":"Procedure"}}]}