{"resourceType":"Bundle","type":"transaction","entry":[{"fullUrl":"urn:uuid:2f5b2f72-ad83-47f2-81c1-09e5c11eeec6","resource":{"resourceType":"Patient","id":"2f5b2f72-ad83-47f2-81c1-09e5c11eeec6","meta":{"profile":["http://hl7.org/fhir/us/core/StructureDefinition/us-core-patient"]},"identifier":[{"system":"urn:trialmatchrx:patient","value":"PAT0001"}],"name":[{"use":"official","family":"PAT0001"}],"gender":"female","birthDate":"1993-01-01"},"request":{"method":"POST","url":"Patient"}},{"fullUrl":"urn:uuid:ea099040-47f3-48ed-85bb-ffaab8d6a213","resource":{"resourceType":"Encounter","id":"ea099040-47f3-48ed-85bb-ffaab8d6a213","status":"finished","class":{"system":"http://terminology.hl7.org/CodeSystem/v3-ActCode","code":"AMB"},"period":{"start":"2025-02-11","end":"2025-02-11"},"subject":{"reference":"urn:uuid:2f5b2f72-ad83-47f2-81c1-09e5c11eeec6"}},"request":{"method":"POST","url":"Encounter"}},{"fullUrl":"urn:uuid:d6f6f03e-2cb6-4668-b115-a7582e96f32c","resource":{"resourceType":"Condition","id":"d6f6f03e-2cb6-4668-b115-a7582e96f32c","clinicalStatus":{"coding":[{"system":"http://terminology.hl7.org/CodeSystem/condition-clinical","code":"active"}]},"verificationStatus":{"coding":[{"system":"http://terminology.hl7.org/CodeSystem/condition-ver-status","code":"confirmed"}]},"category":[{"coding":[{"system":"http://terminology.hl7.org/CodeSystem/condition-category","code":"problem-list-item"}]}],"code":{"coding":[{"system":"http://hl7.org/fhir/sid/icd-10-cm","code":"C25.9","display":"Malignant neoplasm of pancreas, unspecified"},{"system":"http://snomed.info/sct","code":"363418001","display":"Malignant tumor of pancreas"}],"text":"Pancreatic Cancer"},"subject":{"reference":"urn:uuid:2f5b2f72-ad83-47f2-81c1-09e5c11eeec6"},"onsetDateTime":"2025-02-11"},"request":{"method":"POST","url":"Condition"}},{"fullUrl":"urn:uuid:b56ac175-3cc5-47d3-9a3e-9ee19098a85d","resource":{"resourceType":"Observation","id":"b56ac175-3cc5-47d3-9a3e-9ee19098a85d","status":"final","category":[{"coding":[{"system":"http://terminology.hl7.org/CodeSystem/observation-category","code":"laboratory"}]}],"code":{"coding":[{"system":"http://loinc.org","code":"1920-8","display":"Aspartate aminotransferase [Enzymatic activity/volume] in Serum or Plasma"}],"text":"Aspartate aminotransferase [Enzymatic activity/volume] in Serum or Plasma"},"subject":{"reference":"urn:uuid:2f5b2f72-ad83-47f2-81c1-09e5c11eeec6"},"effectiveDateTime":"2025-02-11","valueQuantity":{"value":83.8,"unit":"U/L","system":"http://unitsofmeasure.org"}},"request":{"method":"POST","url":"Observation"}},{"fullUrl":"urn:uuid:ec5db29a-9cd0-4e8f-a794-c9bb55202a5c","resource":{"resourceType":"Observation","id":"ec5db29a-9cd0-4e8f-a794-c9bb55202a5c","status":"final","category":[{"coding":[{"system":"http://terminology.hl7.org/CodeSystem/observation-category","code":"laboratory"}]}],"code":{"coding":[{"system":"http://loinc.org","code":"1742-6","display":"Alanine aminotransferase [Enzymatic activity/volume] in Serum or Plasma"}],"text":"Alanine aminotransferase [Enzymatic activity/volume] in Serum or Plasma"},"subject":{"reference":"urn:uuid:2f5b2f72-ad83-47f2-81c1-09e5c11eeec6"},"effectiveDateTime":"2025-02-11","valueQuantity":{"value":98.7,"unit":"U/L","system":"http://unitsofmeasure.org"}},"request":{"method":"POST","url":"Observation"}},{"fullUrl":"urn:uuid:084a3f69-e238-4abf-8f11-2728a1f51f46","resource":{"resourceType":"Observation","id":"084a3f69-e238-4abf-8f11-2728a1f51f46","status":"final","category":[{"coding":[{"system":"http://terminology.hl7.org/CodeSystem/observation-category","code":"laboratory"}]}],"code":{"coding":[{"system":"http://loinc.org","code":"2160-0","display":"Creatinine [Mass/volume] in Serum or Plasma"}],"text":"Creatinine [Mass/volume] in Serum or Plasma"},"subject":{"reference":"urn:uuid:2f5b2f72-ad83-47f2-81c1-09e5c11eeec6"},"effectiveDateTime":"2025-02-11","valueQuantity":{"value":1.83,"unit":"mg/dL","system":"http://unitsofmeasure.org"}},"request":{"method":"POST","url":"Observation"}},{"fullUrl":"urn:uuid:50cc1328-92c8-44e7-b910-0fd87d31091e","resource":{"resourceType":"Observation","id":"50cc1328-92c8-44e7-b910-0fd87d31091e","status":"final","category":[{"coding":[{"system":"http://terminology.hl7.org/CodeSystem/observation-category","code":"laboratory"}]}],"code":{"coding":[{"system":"http://loinc.org","code":"718-7","display":"Hemoglobin [Mass/volume] in Blood"}],"text":"Hemoglobin [Mass/volume] in Blood"},"subject":{"reference":"urn:uuid:2f5b2f72-ad83-47f2-81c1-09e5c11eeec6"},"effectiveDateTime":"2025-02-11","valueQuantity":{"value":9.05,"unit":"g/dL","system":"http://unitsofmeasure.org"}},"request":{"method":"POST","url":"Observation"}},{"fullUrl":"urn:uuid:10a8eee9-94b8-463b-861b-9c6368009047","resource":{"resourceType":"Observation","id":"10a8eee9-94b8-463b-861b-9c6368009047","status":"final","category":[{"coding":[{"system":"http://terminology.hl7.org/CodeSystem/observation-category","code":"laboratory"}]}],"code":{"coding":[{"system":"http://loinc.org","code":"777-3","display":"Platelets [#/volume] in Blood by Automated count"}],"text":"Platelets [#/volume] in Blood by Automated count"},"subject":{"reference":"urn:uuid:2f5b2f72-ad83-47f2-81c1-09e5c11eeec6"},"effectiveDateTime":"2025-02-11","valueQuantity":{"value":229.86,"unit":"10*9/L","system":"http://unitsofmeasure.org"}},"request":{"method":"POST","url":"Observation"}},{"fullUrl":"urn:uuid:c22fceec-6332-4e5d-8156-483306be9603","resource":{"resourceType":"Observation","id":"c22fceec-6332-4e5d-8156-483306be9603","status":"final","category":[{"coding":[{"system":"http://terminology.hl7.org/CodeSystem/observation-category","code":"laboratory"}]}],"code":{"coding":[{"system":"http://loinc.org","code":"6690-2","display":"Leukocytes [#/volume] in Blood by Automated count"}],"text":"Leukocytes [#/volume] in Blood by Automated count"},"subject":{"reference":"urn:uuid:2f5b2f72-ad83-47f2-81c1-09e5c11eeec6"},"effectiveDateTime":"2025-02-11","valueQuantity":{"value":12.62,"unit":"10*9/L","system":"http://unitsofmeasure.org"}},"request":{"method":"POST","url":"Observation"}},{"fullUrl":"urn:uuid:579f756a-9886-4882-be44-73bc62a822f0","resource":{"resourceType":"Procedure","id":"579f756a-9886-4882-be44-73bc62a822f0","status":"completed","code":{"coding":[{"system":"http://snomed.info/sct","code":"367336001","display":"Chemotherapy"}],"text":"Chemotherapy"},"subject":{"reference":"urn:uuid:2f5b2f72-ad83-47f2-81c1-09e5c11eeec6"},"performedDateTime":"2025-02-11"},"request":{"method":"POST","url":"Procedure"}},{"fullUrl":"urn:uuid:93cb4c53-4c63-4033-9d42-c158e4094b41","resource":{"resourceType":"Procedure","id":"93cb4c53-4c63-4033-9d42-c158e4094b41","status":"completed","code":{"coding":[{"system":"http://snomed.info/sct","code":"387713003","display":"Surgical procedure"}],"text":"Surgical procedure"},"subject":{"reference":"urn:uuid:2f5b2f72-ad83-47f2-81c1-09e5c11eeec6"},"performedDateTime":"2025-02-11"},"request":{"method":"POST","url":"Procedure"}},{"fullUrl":"urn:uuid:d7dc0a24-34d5-4491-a780-ad701d8f5502","resource":{"resourceType":"Procedure","id":"d7dc0a24-34d5-4491-a780-ad701d8f5502","status":"completed","code":{"coding":[{"system":"http://snomed.info/sct","code":"169413002","display":"Hormone therapy"}],"text":"Hormone therapy"},"subject":{"reference":"urn:uuid:2f5b2f72-ad83-47f2-81c1-09e5c11eeec6"},"performedDateTime":"2025-02-11"},"request":{"method":"POST","url":"Procedure"}}]}